pattern_library/__init__.py
pattern_library/pattern_library.py
pattern_library-0.3.dist-info/METADATA
pattern_library-0.3.dist-info/WHEEL
pattern_library-0.3.dist-info/top_level.txt
pattern_library-0.3.dist-info/RECORD
