Metadata-Version: 2.1
Name: pattern-library
Version: 0.3
Summary: A description of your package
Home-page: https://github.com/pr1neeth/pattern_library
Author: Praneeth
Author-email: pr1neethbv@gmail.com
Classifier: Programming Language :: Python :: 3
Classifier: License :: OSI Approved :: MIT License
Classifier: Operating System :: OS Independent
Requires-Python: >=3.6
